{
  "scope_status": "computational_scaffold",
  "readout_status": "simulated_proxy",
  "field_mode": "proxy_convolution_no_pde",
  "physical_amplitude_claim_allowed": false,
  "visualizer": "plotly_standalone_html",
  "duration_ms": 1000.0,
  "dt_ms": 0.1,
  "dtype": "float32",
  "seed": 42,
  "n_neurons": 48,
  "layers": [
    "L2/3",
    "L4",
    "L5",
    "L6"
  ],
  "cell_types": {
    "E": 0.7,
    "PV": 0.15,
    "SST": 0.1,
    "VIP": 0.05
  },
  "mean_population_rate_hz": 0.0011,
  "voltage_range_mv_like": [
    -86.21,
    29.95
  ],
  "all_outputs_finite": true,
  "equations": {
    "source_bookkeeping": "S(t) \u2208 \u211d^{T\u00d7N}",
    "field_handoff": "Y(t) = P\u00b7S(t)",
    "probe_readout": "R_k(t) = Q_k\u00b7Y(t)"
  },
  "html_output": "docs/assets/interactive/v037_source_column_3d.html"
}